array_helpers/__init__.py
array_helpers/array_helper.py
array_helpers/predicate_class.py
array_helpers-0.0.1.dist-info/METADATA
array_helpers-0.0.1.dist-info/WHEEL
array_helpers-0.0.1.dist-info/top_level.txt
array_helpers-0.0.1.dist-info/RECORD
